{"trial_id": "00", "hyperparameters": {"space": [{"class_name": "Int", "config": {"name": "n_layers", "default": null, "conditions": [], "min_value": 4, "max_value": 15, "step": 1, "sampling": "linear"}}, {"class_name": "Int", "config": {"name": "n_units", "default": null, "conditions": [], "min_value": 32, "max_value": 512, "step": 32, "sampling": "linear"}}, {"class_name": "Int", "config": {"name": "epochs", "default": null, "conditions": [], "min_value": 50, "max_value": 1000, "step": 50, "sampling": "linear"}}, {"class_name": "Float", "config": {"name": "penalty", "default": 0.0001, "conditions": [], "min_value": 0.0001, "max_value": 1.0, "step": null, "sampling": "log"}}, {"class_name": "Choice", "config": {"name": "activation", "default": "relu", "conditions": [], "values": ["relu", "elu", "softmax"], "ordered": false}}, {"class_name": "Choice", "config": {"name": "optimizer", "default": "adam", "conditions": [], "values": ["adam", "rmsprop", "adamax"], "ordered": false}}], "values": {"n_layers": 8, "n_units": 384, "epochs": 650, "penalty": 0.00028302752963260723, "activation": "elu", "optimizer": "rmsprop"}}, "metrics": {"metrics": {"loss": {"direction": "min", "observations": [{"value": [5.263121128082275], "step": 47}]}, "val_loss": {"direction": "min", "observations": [{"value": [5.0051984786987305], "step": 47}]}}}, "score": 5.0051984786987305, "best_step": 47, "status": "COMPLETED", "message": null}